microsoft_agents_a365/observability/hosting/__init__.py
microsoft_agents_a365/observability/hosting/scope_helpers/__init__.py
microsoft_agents_a365/observability/hosting/scope_helpers/populate_baggage.py
microsoft_agents_a365/observability/hosting/scope_helpers/populate_invoke_agent_scope.py
microsoft_agents_a365/observability/hosting/scope_helpers/utils.py
microsoft_agents_a365/observability/hosting/token_cache_helpers/__init__.py
microsoft_agents_a365/observability/hosting/token_cache_helpers/agent_token_cache.py
microsoft_agents_a365_observability_hosting-0.2.1.dev9.dist-info/METADATA
microsoft_agents_a365_observability_hosting-0.2.1.dev9.dist-info/WHEEL
microsoft_agents_a365_observability_hosting-0.2.1.dev9.dist-info/top_level.txt
microsoft_agents_a365_observability_hosting-0.2.1.dev9.dist-info/RECORD
