Metadata-Version: 2.4
Name: microsoft-agents-a365-observability-hosting
Version: 0.2.1.dev9
Summary: Hosting components for Agent 365 observability
Author-email: Microsoft <support@microsoft.com>
License: MIT
Project-URL: Homepage, https://github.com/microsoft/Agent365-python
Project-URL: Repository, https://github.com/microsoft/Agent365-python
Project-URL: Issues, https://github.com/microsoft/Agent365-python/issues
Project-URL: Documentation, https://github.com/microsoft/Agent365-python/tree/main/libraries/microsoft-agents-a365-observability-hosting
Keywords: observability,telemetry,tracing,opentelemetry,monitoring,ai,agents,hosting
Classifier: Development Status :: 3 - Alpha
Classifier: Intended Audience :: Developers
Classifier: Programming Language :: Python :: 3
Classifier: Programming Language :: Python :: 3.11
Classifier: Programming Language :: Python :: 3.12
Classifier: Operating System :: OS Independent
Classifier: Topic :: Software Development :: Libraries :: Python Modules
Classifier: Topic :: Scientific/Engineering :: Artificial Intelligence
Classifier: Topic :: System :: Monitoring
Requires-Python: >=3.11
Requires-Dist: microsoft-agents-hosting-core>=0.4.0
Requires-Dist: microsoft-agents-a365-observability-core>=0.0.0
Requires-Dist: opentelemetry-api>=1.36.0
